sakyum/__init__.py
sakyum/api.py
sakyum/base.py
sakyum/blueprint.py
sakyum/database.py
sakyum/utils.py
sakyum/auth/__init__.py
sakyum/auth/admin.py
sakyum/auth/forms.py
sakyum/auth/models.py
sakyum/auth/routes.py
sakyum/contrib/__init__.py
sakyum/mute/__init__.py
sakyum/mute/app.py
sakyum/mute/page.py
sakyum/mute/project.py
sakyum/static/do_nothing.txt
sakyum/static/default_style/css/style.css
sakyum/static/default_style/js/index.js
sakyum/static/default_style/media/alert.png
sakyum/static/default_style/media/default_img.png
sakyum/static/default_style/media/favicon.ico
sakyum/templates/default_errors/400.html
sakyum/templates/default_errors/401.html
sakyum/templates/default_errors/403.html
sakyum/templates/default_errors/404.html
sakyum/templates/default_errors/406.html
sakyum/templates/default_errors/415.html
sakyum/templates/default_errors/429.html
sakyum/templates/default_errors/500.html
sakyum/templates/default_errors/501.html
sakyum/templates/default_errors/502.html
sakyum/templates/default_errors/503.html
sakyum/templates/default_errors/504.html
sakyum/templates/default_page/admin_change_password.html
sakyum/templates/default_page/admin_change_profile_image.html
sakyum/templates/default_page/admin_login.html
sakyum/templates/default_page/admin_register.html
sakyum/templates/default_page/default.html
sakyum/templates/default_page/default_base.html
sakyum/templates/default_page/default_index.html
sakyum-0.0.12.dist-info/LICENSE
sakyum-0.0.12.dist-info/METADATA
sakyum-0.0.12.dist-info/WHEEL
sakyum-0.0.12.dist-info/top_level.txt
sakyum-0.0.12.dist-info/RECORD
